nyrag/__init__.py
nyrag/api.py
nyrag/cli.py
nyrag/config.py
nyrag/deploy.py
nyrag/feed.py
nyrag/logger.py
nyrag/process.py
nyrag/schema.py
nyrag/utils.py
nyrag/crawly/__init__.py
nyrag/crawly/crawly.py
nyrag/crawly/user_agents.py
nyrag/static/chat.css
nyrag/static/chat.js
nyrag/templates/chat.html
nyrag/tests/__init__.py
nyrag/tests/test_config.py
nyrag/tests/test_crawly.py
nyrag/tests/test_feed.py
nyrag/tests/test_schema.py
nyrag/tests/test_utils.py
nyrag-0.0.8.dist-info/licenses/LICENSE
nyrag-0.0.8.dist-info/METADATA
nyrag-0.0.8.dist-info/WHEEL
nyrag-0.0.8.dist-info/entry_points.txt
nyrag-0.0.8.dist-info/top_level.txt
nyrag-0.0.8.dist-info/RECORD
