Metadata-Version: 2.4
Name: nyrag
Version: 0.0.8
Summary: nyrag
Author: abhishek
Project-URL: Homepage, https://github.com/abhishekkrthakur/nyrag
Project-URL: Issues, https://github.com/abhishekkrthakur/nyrag/issues
Keywords: nyrag
Classifier: Development Status :: 5 - Production/Stable
Classifier: License :: OSI Approved :: Apache Software License
Classifier: Operating System :: OS Independent
Classifier: Programming Language :: Python :: 3.10
Classifier: Programming Language :: Python :: 3.11
Classifier: Topic :: Scientific/Engineering :: Artificial Intelligence
Requires-Python: <3.14,>=3.10
License-File: LICENSE
Requires-Dist: rich>=13.0.0
Requires-Dist: fastapi==0.128.0
Requires-Dist: uvicorn==0.40.0
Requires-Dist: pyyaml>=6.0.3
Requires-Dist: markitdown>=0.1.4
Requires-Dist: scrapy>=2.13.4
Requires-Dist: beautifulsoup4>=4.14.3
Requires-Dist: pyvespa>=0.62.0
Requires-Dist: brotli>=1.2.0
Requires-Dist: sentence-transformers>=5.2.0
Requires-Dist: httpx>=0.28.1
Requires-Dist: jinja2>=3.1.6
Requires-Dist: openai>=2.14.0
Requires-Dist: vespacli>=8.620.35
Provides-Extra: dev
Requires-Dist: black>=25.12.0; extra == "dev"
Requires-Dist: isort>=7.0.0; extra == "dev"
Requires-Dist: flake8>=7.3.0; extra == "dev"
Requires-Dist: pytest>=9.0.2; extra == "dev"
Dynamic: license-file
